accipy_data/possible_values.json
accipy.py
accipy-0.0.12.dist-info/LICENSE
accipy-0.0.12.dist-info/METADATA
accipy-0.0.12.dist-info/WHEEL
accipy-0.0.12.dist-info/RECORD
