Metadata-Version: 2.1
Name: accipy
Version: 0.0.12
Summary: Application for querying the National Transportation Safety Board (NTSB) investigations database
Author: Gage Broberg
Author-email: gagebroberg@tamu.edu
Requires-Python: >=3.7,<4.0
Classifier: License :: OSI Approved :: MIT License
Classifier: Operating System :: OS Independent
Classifier: Programming Language :: Python :: 3
Classifier: Programming Language :: Python :: 3.7
Classifier: Programming Language :: Python :: 3.8
Classifier: Programming Language :: Python :: 3.9
Classifier: Programming Language :: Python :: 3.10
Classifier: Programming Language :: Python :: 3.11
Requires-Dist: pandas (>=1.3.5,<2.0.0)
Requires-Dist: python_dateutil (>=2.8.2,<3.0.0)
Requires-Dist: requests (>=2.31.0,<3.0.0)
